expected_cost/__init__.py
expected_cost/calibration.py
expected_cost/data.py
expected_cost/ec.py
expected_cost/psrcal_wrappers.py
expected_cost/utils.py
notebooks/__init__.py
psrcal/__init.__.py
psrcal/__init__.py
psrcal/calibration.py
psrcal/losses.py
psrcal/psr.py
psrcal/utils.py
psrcal/optim/__init__.py
psrcal/optim/example.py
psrcal/optim/fullbatch_optim.py
psrcal/optim/vecmodule.py
expected_cost-1.0.dist-info/LICENSE.md
expected_cost-1.0.dist-info/METADATA
expected_cost-1.0.dist-info/WHEEL
expected_cost-1.0.dist-info/top_level.txt
expected_cost-1.0.dist-info/RECORD
