Metadata-Version: 2.2
Name: expected_cost
Version: 1.0
Summary: Methods for computing the expected cost metric for evaluation of classification systems
Home-page: https://github.com/luferrer/expected_cost
Author: Luciana Ferrer
Classifier: Programming Language :: Python :: 3
Classifier: License :: OSI Approved :: MIT License
Classifier: Operating System :: OS Independent
Requires-Python: >=3.6
License-File: LICENSE.md
Requires-Dist: matplotlib>=3.5.2
Requires-Dist: numpy>=1.24.1
Requires-Dist: scipy>=1.9.1
Requires-Dist: scikit_learn>=1.2.2
